pyautoeios/__init__.py
pyautoeios/_pyautogui_remoteinput_patch.py
pyautoeios/_pyscreeze_cv2_patch.py
pyautoeios/_pyscreeze_remoteinput_patch.py
pyautoeios/eios.py
pyautoeios/hexcodes.py
pyautoeios-0.0.2.dist-info/LICENSE
pyautoeios-0.0.2.dist-info/METADATA
pyautoeios-0.0.2.dist-info/WHEEL
pyautoeios-0.0.2.dist-info/top_level.txt
pyautoeios-0.0.2.dist-info/RECORD
