Metadata-Version: 2.1
Name: pyautoeios
Version: 0.0.2
Summary: automate an old school classic
Home-page: https://github.com/BrettMoan/pyautoeios
Author: Brett Moan
Author-email: brett.moan@gmail.com
License: BSD 3-Clause
Project-URL: Bug Tracker, https://github.com/BrettMoan/pyautoeios/issues
Project-URL: Changelog, https://github.com/BrettMoan/pyautoeios/blob/master/CHANGELOG.md
Keywords: {keywords}
Platform: any
Classifier: Development Status :: 2 - Pre-Alpha
Classifier: Intended Audience :: Developers
Classifier: Intended Audience :: Science/Research
Classifier: License :: OSI Approved :: BSD License
Classifier: Environment :: Win32 (MS Windows)
Classifier: Operating System :: Microsoft :: Windows :: Windows 10
Classifier: Programming Language :: Python :: 3.8
Classifier: Programming Language :: Python :: Implementation :: CPython
Classifier: Topic :: Software Development :: Libraries :: Python Modules
Classifier: Topic :: Games/Entertainment
Classifier: Topic :: Scientific/Engineering :: Image Recognition
Classifier: Topic :: Scientific/Engineering :: Image Processing
